napari_lf/__init__.py
napari_lf/_version.py
napari_lf/_widgetLF.py
napari_lf/_widgetLF_gui.py
napari_lf/_widgetLF_test.py
napari_lf/_widgetLF_vals.py
napari_lf/main.py
napari_lf/napari.yaml
napari_lf/_tests/__init__.py
napari_lf/_tests/test_widgetLF.py
napari_lf/examples/GUVExperim1/DarkFrame_GUVExperim1.tif
napari_lf/examples/GUVExperim1/Lightfield_GUVExperim1.tif
napari_lf/examples/GUVExperim1/README
napari_lf/examples/GUVExperim1/Radiometry_GUVExperim1.tif
napari_lf/examples/GUVExperim1/metadata.txt
napari_lf/examples/antleg/README
napari_lf/examples/antleg/dark_frame.tif
napari_lf/examples/antleg/light_field.png
napari_lf/examples/antleg/radiometry_frame.png
napari_lf/examples/seaurchin/dark_frame.tif
napari_lf/examples/seaurchin/light_field.tif
napari_lf/examples/seaurchin/metadata.txt
napari_lf/examples/seaurchin/radiometry_frame.tif
napari_lf/lfa/__init__.py
napari_lf/lfa/lfcalibrate.py
napari_lf/lfa/lfdeconvolve.py
napari_lf/lfa/lfproject.py
napari_lf/lfa/lfrectify.py
napari_lf/lfa/main_train_neural_net.ipynb
napari_lf/lfa/lflib/__init__.py
napari_lf/lfa/lflib/imageio.py
napari_lf/lfa/lflib/lfexceptions.py
napari_lf/lfa/lflib/lightfield.py
napari_lf/lfa/lflib/linear_operators.py
napari_lf/lfa/lflib/lsmr.py
napari_lf/lfa/lflib/multiscale3d.py
napari_lf/lfa/lflib/optics.py
napari_lf/lfa/lflib/postfilter.py
napari_lf/lfa/lflib/util.py
napari_lf/lfa/lflib/volume.py
napari_lf/lfa/lflib/wave_optics.py
napari_lf/lfa/lflib/calibration/__init__.py
napari_lf/lfa/lflib/calibration/grid.py
napari_lf/lfa/lflib/calibration/imaging.py
napari_lf/lfa/lflib/calibration/models.py
napari_lf/lfa/lflib/calibration/ransac.py
napari_lf/lfa/lflib/solvers/__init__.py
napari_lf/lfa/lflib/solvers/admm.py
napari_lf/lfa/lflib/solvers/amp.py
napari_lf/lfa/lflib/solvers/conjugate_gradient.py
napari_lf/lfa/lflib/solvers/lsqr.py
napari_lf/lfa/lflib/solvers/mrnsd.py
napari_lf/lfa/lflib/solvers/richardson_lucy.py
napari_lf/lfa/lflib/solvers/sirt.py
napari_lf/lfa/neural_nets/LFMNet.py
napari_LF-0.1.7.dist-info/LICENSE
napari_LF-0.1.7.dist-info/METADATA
napari_LF-0.1.7.dist-info/WHEEL
napari_LF-0.1.7.dist-info/entry_points.txt
napari_LF-0.1.7.dist-info/top_level.txt
napari_LF-0.1.7.dist-info/RECORD
