Metadata-Version: 2.1
Name: napari-LF
Version: 0.1.7
Summary: Light field imaging plugin for napari
Home-page: https://github.com/PolarizedLightFieldMicroscopy/napari-LF
Author: Geneva Schlafly, Amitabh Verma, Rudolf Oldenbourg
Author-email: gschlafly@uchicago.edu, averma@mbl.edu, rudolfo@mbl.edu
License: BSD-3-Clause
Project-URL: Bug Tracker, https://github.com/PolarizedLightFieldMicroscopy/napari-LF/issues
Project-URL: Documentation, https://github.com/PolarizedLightFieldMicroscopy/napari-LF#README.md
Project-URL: Source Code, https://github.com/PolarizedLightFieldMicroscopy/napari-LF
Project-URL: User Support, https://github.com/PolarizedLightFieldMicroscopy/napari-LF/issues
Classifier: Development Status :: 2 - Pre-Alpha
Classifier: Intended Audience :: Developers
Classifier: Intended Audience :: Science/Research
Classifier: Framework :: napari
Classifier: Topic :: Scientific/Engineering :: Image Processing
Classifier: Programming Language :: Python
Classifier: Programming Language :: Python :: 3
Classifier: Programming Language :: Python :: 3.7
Classifier: Programming Language :: Python :: 3.8
Classifier: Programming Language :: Python :: 3.9
Classifier: Programming Language :: Python :: 3.10
Classifier: Operating System :: OS Independent
Classifier: License :: OSI Approved :: BSD License
Requires-Python: >=3.7
License-File: LICENSE
Requires-Dist: numpy
Requires-Dist: h5py
Requires-Dist: pyopencl
Requires-Dist: napari[all]
Requires-Dist: opencv-python
Requires-Dist: torch
Requires-Dist: torchvision
Requires-Dist: pytorch-lightning
